{
    "pageTitle": {
        "inner": "Welcome to the Demo Site"
    },
    "heroSubtitle": {
        "inner": "A simple demonstration of a generic website layout."
    },
    "aboutLinkText": {
        "inner": "Learn More About Us",
        "href": "\/about"
    },
    "blogLinkText": {
        "inner": "Read Our Blog",
        "href": "\/blog"
    },
    "listItems": [
        {
            "itemTitle": {
                "inner": "FIRST LIST ITEM"
            },
            "itemTags": [
                {
                    "tagName": {
                        "inner": "tag#1"
                    }
                },
                {
                    "tagName": {
                        "inner": "tag#2"
                    }
                }
            ]
        },
        {
            "itemTitle": {
                "inner": "SECOND LIST ITEM"
            },
            "itemTags": {
                "0": {
                    "tagName": {
                        "inner": "tag#3"
                    }
                },
                "2": {
                    "tagName": {
                        "inner": "tag#4"
                    }
                }
            }
        }
    ]
}